Metadata-Version: 1.0
Name: ppc-distributions
Version: 1.0
Summary: Gaussian and Binomial distributions
Home-page: UNKNOWN
Author: ppuentec
Author-email: career.development.miami@gmail.com
License: UNKNOWN
Platform: UNKNOWN
